boomi/__init__.py
boomi/sdk.py
boomi/sdk_async.py
boomi/hooks/__init__.py
boomi/hooks/hook.py
boomi/models/__init__.py
boomi/models/account.py
boomi/models/account_bulk_request.py
boomi/models/account_bulk_response.py
boomi/models/account_cloud_attachment_properties.py
boomi/models/account_cloud_attachment_properties_async_response.py
boomi/models/account_cloud_attachment_quota.py
boomi/models/account_cloud_attachment_quota_bulk_request.py
boomi/models/account_cloud_attachment_quota_bulk_response.py
boomi/models/account_expression.py
boomi/models/account_group.py
boomi/models/account_group_account.py
boomi/models/account_group_account_expression.py
boomi/models/account_group_account_grouping_expression.py
boomi/models/account_group_account_query_config.py
boomi/models/account_group_account_query_response.py
boomi/models/account_group_account_simple_expression.py
boomi/models/account_group_bulk_request.py
boomi/models/account_group_bulk_response.py
boomi/models/account_group_expression.py
boomi/models/account_group_grouping_expression.py
boomi/models/account_group_integration_pack.py
boomi/models/account_group_integration_pack_bulk_request.py
boomi/models/account_group_integration_pack_bulk_response.py
boomi/models/account_group_integration_pack_expression.py
boomi/models/account_group_integration_pack_query_config.py
boomi/models/account_group_integration_pack_query_response.py
boomi/models/account_group_query_config.py
boomi/models/account_group_query_response.py
boomi/models/account_group_simple_expression.py
boomi/models/account_group_user_role.py
boomi/models/account_group_user_role_expression.py
boomi/models/account_group_user_role_grouping_expression.py
boomi/models/account_group_user_role_query_config.py
boomi/models/account_group_user_role_query_response.py
boomi/models/account_group_user_role_simple_expression.py
boomi/models/account_grouping_expression.py
boomi/models/account_query_config.py
boomi/models/account_query_response.py
boomi-1.2.8.dist-info/licenses/LICENSE
boomi-1.2.8.dist-info/METADATA
boomi-1.2.8.dist-info/WHEEL
boomi-1.2.8.dist-info/top_level.txt
boomi-1.2.8.dist-info/RECORD
