Metadata-Version: 2.4
Name: boomi
Version: 1.2.8
Summary: Python SDK for Boomi Platform API - provides programmatic access to Boomi Enterprise Platform functionality.
License-Expression: MIT
Requires-Python: >=3.9
License-File: LICENSE
Requires-Dist: requests>=2.31.0
Requires-Dist: python-dotenv>=1.0.0
Provides-Extra: dev
Requires-Dist: python-dotenv>=1.0.0; extra == "dev"
Dynamic: license-file
